sandworm/version.py
sandworm/sandworm.py
sandworm/sandworm_main.py
sandworm/__init__.py
sandworm/cli.py
sandworm/__about__.py
sandworm/config/default.yaml
sandworm-0.1.0.dev0.dist-info/RECORD
sandworm-0.1.0.dev0.dist-info/metadata.json
sandworm-0.1.0.dev0.dist-info/WHEEL
sandworm-0.1.0.dev0.dist-info/entry_points.txt
sandworm-0.1.0.dev0.dist-info/DESCRIPTION.rst
sandworm-0.1.0.dev0.dist-info/top_level.txt
sandworm-0.1.0.dev0.dist-info/METADATA
