Metadata-Version: 2.0
Name: sandworm
Version: 0.1.0.dev0
Summary: Comming soon
Home-page: https://github.com/zcutlip/sandworm.git
License: UNKNOWN
Platform: UNKNOWN
Requires-Python: >=3.7
